{
  "name": "My workflow",
  "nodes": [
    {
      "parameters": {
        "rule": {
          "interval": [
            {
              "field": "weeks",
              "triggerAtDay": [
                1
              ],
              "triggerAtHour": 9
            }
          ]
        }
      },
      "type": "n8n-nodes-base.scheduleTrigger",
      "typeVersion": 1.3,
      "position": [
        0,
        0
      ],
      "id": "2584bf9b-ece6-414e-ae3a-43262cc900d4",
      "name": "Schedule Trigger"
    },
    {
      "parameters": {
        "resource": "donkiSolarFlare",
        "additionalFields": {
          "startDate": "={{ $today.minus(7, 'days') }}"
        }
      },
      "type": "n8n-nodes-base.nasa",
      "typeVersion": 1,
      "position": [
        208,
        0
      ],
      "id": "f143482d-de4c-4786-b865-48a9cb16060e",
      "name": "Get a DONKI solar flare",
      "credentials": {
        "nasaApi": {
          "id": "isQoP58vgke0qkMn",
          "name": "NASA account"
        }
      }
    },
    {
      "parameters": {
        "conditions": {
          "options": {
            "caseSensitive": true,
            "leftValue": "",
            "typeValidation": "strict",
            "version": 3
          },
          "conditions": [
            {
              "id": "f7283834-2ad0-4760-baa8-1937ce679d60",
              "leftValue": "={{ $json.classType }}",
              "rightValue": "M5",
              "operator": {
                "type": "string",
                "operation": "contains"
              }
            }
          ],
          "combinator": "and"
        },
        "options": {}
      },
      "type": "n8n-nodes-base.if",
      "typeVersion": 2.3,
      "position": [
        416,
        0
      ],
      "id": "06aafb06-0634-45f9-8f04-dbcfa6042925",
      "name": "If"
    },
    {
      "parameters": {
        "resource": "request",
        "operation": "send",
        "binId": "1766878032640-3999199715908",
        "binContent": "=There was a solar flare of class {{ $json.classType }}",
        "requestOptions": {}
      },
      "type": "n8n-nodes-base.postBin",
      "typeVersion": 1,
      "position": [
        624,
        -96
      ],
      "id": "ee79f338-e34d-4621-889e-a81cb1dd897d",
      "name": "Send a request"
    },
    {
      "parameters": {
        "resource": "request",
        "operation": "send",
        "binId": "1766878032640-3999199715908",
        "binContent": "=There was a solar flare of class {{ $json.classType }}",
        "requestOptions": {}
      },
      "type": "n8n-nodes-base.postBin",
      "typeVersion": 1,
      "position": [
        624,
        96
      ],
      "id": "74024a21-25d3-47d4-aa2e-9df57deffd18",
      "name": "Send a request1"
    }
  ],
  "pinData": {},
  "connections": {
    "Schedule Trigger": {
      "main": [
        [
          {
            "node": "Get a DONKI solar flare",
            "type": "main",
            "index": 0
          }
        ]
      ]
    },
    "Get a DONKI solar flare": {
      "main": [
        [
          {
            "node": "If",
            "type": "main",
            "index": 0
          }
        ]
      ]
    },
    "If": {
      "main": [
        [
          {
            "node": "Send a request",
            "type": "main",
            "index": 0
          }
        ],
        [
          {
            "node": "Send a request1",
            "type": "main",
            "index": 0
          }
        ]
      ]
    }
  },
  "active": false,
  "settings": {
    "executionOrder": "v1",
    "availableInMCP": false
  },
  "versionId": "0fdf4a8d-0c17-4a37-8c9b-84265ca52903",
  "meta": {
    "templateCredsSetupCompleted": true,
    "instanceId": "dd93f07c4d71591b4b40bb4fae3682563386a657f3696d2a1892a06970259711"
  },
  "id": "n81H7piNNcOksmjo",
  "tags": []
}
